{
    "2024-10": {
      "text": "2024年10月员工薪资",
      "subtext": "部门细分",
      "xAxis": ["工程", "销售", "市场营销", "HR"],
      "yAxis": [150000, 120000, 90000, 75000]
    },
    "2024-09": {
      "text": "2024年9月员工薪资",
      "subtext": "部门细分",
      "xAxis": ["工程", "销售", "市场营销", "HR"],
      "yAxis": [148000, 118000, 89000, 74000]
    },
    "2024-08": {
      "text": "2024年8月员工薪资",
      "subtext": "部门细分",
      "xAxis": ["工程", "销售", "市场营销", "HR", "后勤"],
      "yAxis": [145000, 115000, 88000, 72000, 60000]
    },
    "default": {
      "text": "所选月份的薪资数据不可用",
      "subtext": "",
      "xAxis": [],
      "yAxis": []
    }
  }
  